CHANGES.rst
MANIFEST.in
README.rst
setup.py
docs/LICENSE.GPL
docs/LICENSE.txt
plone/__init__.py
plone.formwidget.captcha.egg-info/PKG-INFO
plone.formwidget.captcha.egg-info/SOURCES.txt
plone.formwidget.captcha.egg-info/dependency_links.txt
plone.formwidget.captcha.egg-info/entry_points.txt
plone.formwidget.captcha.egg-info/namespace_packages.txt
plone.formwidget.captcha.egg-info/not-zip-safe
plone.formwidget.captcha.egg-info/requires.txt
plone.formwidget.captcha.egg-info/top_level.txt
plone/formwidget/__init__.py
plone/formwidget/captcha/README.txt
plone/formwidget/captcha/__init__.py
plone/formwidget/captcha/captcha_input.pt
plone/formwidget/captcha/configure.zcml
plone/formwidget/captcha/interfaces.py
plone/formwidget/captcha/meta.zcml
plone/formwidget/captcha/testing.zcml
plone/formwidget/captcha/tests.py
plone/formwidget/captcha/validator.py
plone/formwidget/captcha/widget.pt
plone/formwidget/captcha/widget.py
plone/formwidget/captcha/browser/__init__.py
plone/formwidget/captcha/browser/arevmoit.bdf
plone/formwidget/captcha/browser/captcha.py
plone/formwidget/captcha/browser/captcha.txt
plone/formwidget/captcha/browser/configure.zcml
plone/formwidget/captcha/browser/interfaces.py
plone/formwidget/captcha/browser/tests.py
plone/formwidget/captcha/browser/waveIndex.zip
plone/formwidget/captcha/demo/__init__.py
plone/formwidget/captcha/demo/configure.zcml
plone/formwidget/captcha/demo/form.py
plone/formwidget/captcha/locales/__init__.py
plone/formwidget/captcha/locales/plone.formwidget.captcha.pot
plone/formwidget/captcha/locales/plone.pot
plone/formwidget/captcha/locales/cs/LC_MESSAGES/plone.formwidget.captcha.mo
plone/formwidget/captcha/locales/cs/LC_MESSAGES/plone.formwidget.captcha.po
plone/formwidget/captcha/locales/es/LC_MESSAGES/plone.formwidget.captcha.mo
plone/formwidget/captcha/locales/es/LC_MESSAGES/plone.formwidget.captcha.po
plone/formwidget/captcha/locales/fr/LC_MESSAGES/plone.formwidget.captcha.mo
plone/formwidget/captcha/locales/fr/LC_MESSAGES/plone.formwidget.captcha.po
plone/formwidget/captcha/locales/nl/LC_MESSAGES/plone.formwidget.captcha.mo
plone/formwidget/captcha/locales/nl/LC_MESSAGES/plone.formwidget.captcha.po
plone/formwidget/captcha/locales/pt_BR/LC_MESSAGES/plone.formwidget.captcha.mo
plone/formwidget/captcha/locales/pt_BR/LC_MESSAGES/plone.formwidget.captcha.po
