Metadata-Version: 1.1
Name: plone.formwidget.captcha
Version: 1.0.3
Summary: Captcha widget for Plone.
Home-page: http://pypi.python.org/pypi/plone.formwidget.captcha
Author: Timo Stollenwerk - Plone Foundation
Author-email: plone-developers@lists.sourceforge.net
License: GPL
Keywords: plone discussion plone.app.discussion spam captcha
Platform: UNKNOWN
Classifier: Development Status :: 5 - Production/Stable
Classifier: Environment :: Web Environment
Classifier: Framework :: Plone
Classifier: Framework :: Plone :: 4.1
Classifier: Framework :: Plone :: 4.2
Classifier: Framework :: Plone :: 4.3
Classifier: License :: OSI Approved :: GNU General Public License (GPL)
Classifier: Operating System :: OS Independent
Classifier: Programming Language :: Python
Classifier: Programming Language :: Python :: 2.6
Classifier: Programming Language :: Python :: 2.7
Classifier: Topic :: Software Development :: Libraries :: Python Modules
